setup.py
upload_hdkylin.egg-info/PKG-INFO
upload_hdkylin.egg-info/SOURCES.txt
upload_hdkylin.egg-info/dependency_links.txt
upload_hdkylin.egg-info/top_level.txt
utils/__init__.py
utils/edittorrent/__init__.py
utils/edittorrent/edittorrent.py
utils/img_upload/__init__.py
utils/img_upload/chevereto.py
utils/img_upload/fapping_emp.py
utils/img_upload/imgbox.py
utils/img_upload/imgupload.py
utils/img_upload/ptpimg.py
utils/img_upload/redleaves.py
utils/img_upload/rousi.py
utils/img_upload/sharkimg.py
utils/img_upload/smms.py
utils/mediafile/__init__.py
utils/mediafile/douban_book.py
utils/mediafile/douban_movie.py
utils/mediafile/doubaninfo.py
utils/mediafile/maketorrent.py
utils/mediafile/mediafile.py
utils/para_ctrl/__init__.py
utils/para_ctrl/para_ctrl.py
utils/para_ctrl/readargs.py
utils/para_ctrl/readyaml.py
utils/pathinfo/__init__.py
utils/pathinfo/pathinfo.py
utils/rss_ctrl/__init__.py
utils/seed_machine/__init__.py
utils/seed_machine/seed_machine.py
utils/signer/__init__.py
utils/site/__init__.py
utils/site/site.py
utils/uploader/__init__.py
utils/uploader/audience_upload.py
utils/uploader/auto_upload.py
utils/uploader/carpt_upload.py
utils/uploader/dajiao_upload.py
utils/uploader/hares_upload.py
utils/uploader/hdfans_upload.py
utils/uploader/hdkylin_upload.py
utils/uploader/hdpt_upload.py
utils/uploader/hdsky_upload.py
utils/uploader/hdvideo_upload.py
utils/uploader/hhclub_upload.py
utils/uploader/ihdbits_upload.py
utils/uploader/lemonhd_upload.py
utils/uploader/mteam_upload.py
utils/uploader/pandapt_upload.py
utils/uploader/piggo_upload.py
utils/uploader/pter_upload.py
utils/uploader/ptvicomo_upload.py
utils/uploader/redleaves_upload.py
utils/uploader/rousi_upload.py
utils/uploader/sharkpt_upload.py
utils/uploader/ssd_upload.py
utils/uploader/upload_tools.py
utils/uploader/wintersakura_upload.py
utils/uploader/zhuque_upload.py
utils/uploader/zmpt_upload.py