Metadata-Version: 2.1
Name: upload_hdkylin
Version: 0.0.1
Summary: 一键转种
Home-page: 
Author: moyan
Author-email: 
